aiohttp_openapi/__init__.py
aiohttp_openapi/_web_util.py
aiohttp_openapi/swagger_ui.py
aiohttp_openapi/contrib-ui/dw-latest-swagger
aiohttp_openapi/contrib-ui/swagger-ui/LICENSE
aiohttp_openapi/contrib-ui/swagger-ui/NOTICE
aiohttp_openapi/contrib-ui/swagger-ui/VERSION
aiohttp_openapi/contrib-ui/swagger-ui/favicon-16x16.png
aiohttp_openapi/contrib-ui/swagger-ui/favicon-32x32.png
aiohttp_openapi/contrib-ui/swagger-ui/swagger-ui-bundle.js
aiohttp_openapi/contrib-ui/swagger-ui/swagger-ui-standalone-preset.js
aiohttp_openapi/contrib-ui/swagger-ui/swagger-ui.css
aiohttp_openapi/tests/test_get_operation.py
aiohttp_openapi/tests/test_openapi_app.py
aiohttp_openapi/tests/test_swagger_ui.py
aiohttp_openapi/tests/util.py
aiohttp_openapi_ermelo-2.0.dist-info/licenses/LICENSE
aiohttp_openapi_ermelo-2.0.dist-info/METADATA
aiohttp_openapi_ermelo-2.0.dist-info/WHEEL
aiohttp_openapi_ermelo-2.0.dist-info/top_level.txt
aiohttp_openapi_ermelo-2.0.dist-info/RECORD
