Metadata-Version: 2.4
Name: aiohttp-openapi-ermelo
Version: 2.0
Summary: Builds openapi schemas for aiohttp apps.
License-Expression: Apache-2.0
Project-URL: HomePage, https://github.com/garyvdm/aiohttp-openapi-ermelo
Classifier: Development Status :: 5 - Production/Stable
Classifier: Intended Audience :: Developers
Classifier: Programming Language :: Python :: 3
Classifier: Framework :: AsyncIO
Classifier: Topic :: Internet :: WWW/HTTP
Requires-Python: >=3.11
License-File: LICENSE
Requires-Dist: aiohttp
Requires-Dist: pydantic
Requires-Dist: openapi-pydantic
Provides-Extra: test
Requires-Dist: pytest; extra == "test"
Requires-Dist: pytest-aiohttp; extra == "test"
Requires-Dist: pytest-playwright-asyncio; extra == "test"
Requires-Dist: mypy; extra == "test"
Requires-Dist: types-PyYAML; extra == "test"
Requires-Dist: pytest-cov; extra == "test"
Provides-Extra: yaml
Requires-Dist: pyyaml; extra == "yaml"
Dynamic: license-file
